odoo8_addon_shopinvader_reset_password-8.0.1.0.0.99.dev3-py3.8-nspkg.pth
odoo_addons/shopinvader_reset_password/README.rst
odoo_addons/shopinvader_reset_password/__init__.py
odoo_addons/shopinvader_reset_password/__openerp__.py
odoo_addons/shopinvader_reset_password/models/__init__.py
odoo_addons/shopinvader_reset_password/models/partner.py
odoo_addons/shopinvader_reset_password/services/__init__.py
odoo_addons/shopinvader_reset_password/services/sign.py
odoo_addons/shopinvader_reset_password/views/partner_view.xml
odoo_addons/shopinvader_reset_password/wizards/__init__.py
odoo_addons/shopinvader_reset_password/wizards/reset_password.py
odoo_addons/shopinvader_reset_password/wizards/reset_password_view.xml
odoo8_addon_shopinvader_reset_password-8.0.1.0.0.99.dev3.dist-info/METADATA
odoo8_addon_shopinvader_reset_password-8.0.1.0.0.99.dev3.dist-info/WHEEL
odoo8_addon_shopinvader_reset_password-8.0.1.0.0.99.dev3.dist-info/namespace_packages.txt
odoo8_addon_shopinvader_reset_password-8.0.1.0.0.99.dev3.dist-info/top_level.txt
odoo8_addon_shopinvader_reset_password-8.0.1.0.0.99.dev3.dist-info/RECORD
